betamax_matchers/__init__.py
betamax_matchers/_compat.py
betamax_matchers/form_urlencoded.py
betamax_matchers/json_body.py
betamax_matchers/multipart.py
betamax_matchers-0.4.0.dist-info/DESCRIPTION.rst
betamax_matchers-0.4.0.dist-info/METADATA
betamax_matchers-0.4.0.dist-info/RECORD
betamax_matchers-0.4.0.dist-info/WHEEL
betamax_matchers-0.4.0.dist-info/metadata.json
betamax_matchers-0.4.0.dist-info/top_level.txt
