Metadata-Version: 2.0
Name: betamax-matchers
Version: 0.4.0
Summary: A VCR imitation for python-requests
Home-page: https://github.com/sigmavirus24/betamax_matchers
Author: Ian Cordasco
Author-email: graffatcolmingov@gmail.com
License: Copyright 2014 Ian Cordasco
Requires-Dist: betamax (>=0.3.2)
Requires-Dist: requests-toolbelt (>=0.4.0)
